langchain_text_splitters/__init__.py
langchain_text_splitters/base.py
langchain_text_splitters/character.py
langchain_text_splitters/html.py
langchain_text_splitters/json.py
langchain_text_splitters/konlpy.py
langchain_text_splitters/latex.py
langchain_text_splitters/markdown.py
langchain_text_splitters/nltk.py
langchain_text_splitters/py.typed
langchain_text_splitters/python.py
langchain_text_splitters/sentence_transformers.py
langchain_text_splitters/spacy.py
langchain_text_splitters/xsl/converting_to_header.xslt
langchain_text_splitters/xsl/html_chunks_with_headers.xslt
gigachain_text_splitters-0.2.3.dist-info/METADATA
gigachain_text_splitters-0.2.3.dist-info/WHEEL
gigachain_text_splitters-0.2.3.dist-info/RECORD
