Metadata-Version: 2.1
Name: gigachain-text-splitters
Version: 0.2.3
Summary: GigaChain text splitting utilities
Home-page: https://github.com/ai-forever/gigachain
License: MIT
Requires-Python: >=3.8.1,<4.0
Classifier: License :: OSI Approved :: MIT License
Classifier: Programming Language :: Python :: 3
Classifier: Programming Language :: Python :: 3.9
Classifier: Programming Language :: Python :: 3.10
Classifier: Programming Language :: Python :: 3.11
Classifier: Programming Language :: Python :: 3.12
Requires-Dist: gigachain-core (>=0.2.10,<0.3.0)
Project-URL: Repository, https://github.com/ai-forever/gigachain
Project-URL: Release Notes, https://github.com/ai-forever/gigachain/releases?q=tag%3A%22gigachain-text-splitters%3D%3D0%22&expanded=true
Project-URL: Source Code, https://github.com/ai-forever/gigachain/tree/master/libs/text-splitters
